onlytld/__init__.py
onlytld/__version__.py
onlytld/data.py
onlytld/functions.py
onlytld/list.dat
onlytld-0.0.6.dist-info/LICENSE
onlytld-0.0.6.dist-info/WHEEL
onlytld-0.0.6.dist-info/METADATA
onlytld-0.0.6.dist-info/RECORD
