Metadata-Version: 2.1
Name: onlytld
Version: 0.0.6
Summary: 
Home-page: https://github.com/abersheeran/onlytld
License: Apache-2.0
Author: abersheeran
Author-email: me@abersheeran.com
Requires-Python: >=3.5,<4.0
Classifier: License :: OSI Approved :: Apache Software License
Classifier: Programming Language :: Python :: 3
Classifier: Programming Language :: Python :: 3.5
Classifier: Programming Language :: Python :: 3.6
Classifier: Programming Language :: Python :: 3.7
Classifier: Programming Language :: Python :: 3.8
Project-URL: Documentation, https://github.com/abersheeran/onlytld
Project-URL: Repository, https://github.com/abersheeran/onlytld
